Workbook

Sheet Cover
A1: Meridia Cold SL · valuation model
A2: Version | C2: v01 · reference (end of Session 1)
A4: Colour convention
A5: Blue · typed input
A6: Black · formula
A7: Green · link to another sheet
A8: Red · external link or warning
A9: Sign convention: costs and investments are shown as positive numbers; formulas subtract them.
A11: Model check | C11: =IF(Checks!C12=0,"OK","ERROR") -> OK
A13: Enterprise value | C13: =Calc!C27 -> 159.35839 | D13: €m
A14: Equity value | C14: =Calc!C29 -> 99.35839 | D14: €m
A15: Value per share | C15: =Calc!C31 -> 2.4839598 | D15: € per share

Sheet Inputs
A1: Inputs · every typed number lives here
A2: Last actual year | C2: 2025
A4: Year | F4: 2023 | G4: =F4+1 -> 2024 | H4: =G4+1 -> 2025 | I4: =H4+1 -> 2026 | J4: =I4+1 -> 2027 | K4: =J4+1 -> 2028
A5: Actual flag | F5: =IF(F4<=$C$2,1,0) -> 1 | G5: =IF(G4<=$C$2,1,0) -> 1 | H5: =IF(H4<=$C$2,1,0) -> 1 | I5: =IF(I4<=$C$2,1,0) -> 0 | J5: =IF(J4<=$C$2,1,0) -> 0 | K5: =IF(K4<=$C$2,1,0) -> 0
A6: Forecast flag | F6: =1-F5 -> 0 | G6: =1-G5 -> 0 | H6: =1-H5 -> 0 | I6: =1-I5 -> 1 | J6: =1-J5 -> 1 | K6: =1-K5 -> 1
A8: Revenue | B8: €m | F8: 160.2 | G8: 171 | H8: 180.4
A9: EBITDA | B9: €m | F9: 23.2 | G9: 26.2 | H9: 29
A10: D&A | B10: €m | F10: 9.6 | G10: 10.1 | H10: 10.6
A11: Capex | B11: €m | F11: 12 | G11: 13.5 | H11: 14.2
A12: Increase in NWC | B12: €m | F12: 1.2 | G12: 1.4 | H12: 1.1
A13: Net debt | B13: €m | F13: 62 | G13: 60.5 | H13: 60
A14: Shares | B14: m | F14: 40 | G14: 40 | H14: 40
A16: Tax rate | B16: % | C16: 0.24
A18: Revenue growth | B18: % | C18: 0.067
A19: EBITDA margin | B19: % | C19: 0.161
A20: D&A growth | B20: % | C20: 0.05
A21: Capex, % of revenue | B21: % | C21: 0.08
A22: NWC, % of the revenue increase | B22: % | C22: 0.1
A24: WACC | B24: % | C24: 0.085
A25: Terminal growth | B25: % | C25: 0.02

Sheet Calc
A1: Calc · formulas only
A4: Year | F4: =Inputs!F4 -> 2023 | G4: =Inputs!G4 -> 2024 | H4: =Inputs!H4 -> 2025 | I4: =Inputs!I4 -> 2026 | J4: =Inputs!J4 -> 2027 | K4: =Inputs!K4 -> 2028
A5: Actual flag | F5: =Inputs!F5 -> 1 | G5: =Inputs!G5 -> 1 | H5: =Inputs!H5 -> 1 | I5: =Inputs!I5 -> 0 | J5: =Inputs!J5 -> 0 | K5: =Inputs!K5 -> 0
A6: Forecast flag | F6: =Inputs!F6 -> 0 | G6: =Inputs!G6 -> 0 | H6: =Inputs!H6 -> 0 | I6: =Inputs!I6 -> 1 | J6: =Inputs!J6 -> 1 | K6: =Inputs!K6 -> 1
A8: Revenue | B8: €m | F8: =F$5*Inputs!F8+F$6*E8*(1+Inputs!$C$18) -> 160.2 | G8: =G$5*Inputs!G8+G$6*F8*(1+Inputs!$C$18) -> 171 | H8: =H$5*Inputs!H8+H$6*G8*(1+Inputs!$C$18) -> 180.4 | I8: =I$5*Inputs!I8+I$6*H8*(1+Inputs!$C$18) -> 192.4868 | J8: =J$5*Inputs!J8+J$6*I8*(1+Inputs!$C$18) -> 205.38342 | K8: =K$5*Inputs!K8+K$6*J8*(1+Inputs!$C$18) -> 219.1441
A9: Revenue growth | B9: % | G9: =G8/F8-1 -> 0.06741573 | H9: =H8/G8-1 -> 0.05497076 | I9: =I8/H8-1 -> 0.067 | J9: =J8/I8-1 -> 0.067 | K9: =K8/J8-1 -> 0.067
A10: EBITDA | B10: €m | F10: =F$5*Inputs!F9+F$6*F8*Inputs!$C$19 -> 23.2 | G10: =G$5*Inputs!G9+G$6*G8*Inputs!$C$19 -> 26.2 | H10: =H$5*Inputs!H9+H$6*H8*Inputs!$C$19 -> 29 | I10: =I$5*Inputs!I9+I$6*I8*Inputs!$C$19 -> 30.990375 | J10: =J$5*Inputs!J9+J$6*J8*Inputs!$C$19 -> 33.06673 | K10: =K$5*Inputs!K9+K$6*K8*Inputs!$C$19 -> 35.282201
A11: EBITDA margin | B11: % | F11: =F10/F8 -> 0.14481898 | G11: =G10/G8 -> 0.15321637 | H11: =H10/H8 -> 0.16075388 | I11: =I10/I8 -> 0.161 | J11: =J10/J8 -> 0.161 | K11: =K10/K8 -> 0.161
A12: D&A | B12: €m | F12: =F$5*Inputs!F10+F$6*E12*(1+Inputs!$C$20) -> 9.6 | G12: =G$5*Inputs!G10+G$6*F12*(1+Inputs!$C$20) -> 10.1 | H12: =H$5*Inputs!H10+H$6*G12*(1+Inputs!$C$20) -> 10.6 | I12: =I$5*Inputs!I10+I$6*H12*(1+Inputs!$C$20) -> 11.13 | J12: =J$5*Inputs!J10+J$6*I12*(1+Inputs!$C$20) -> 11.6865 | K12: =K$5*Inputs!K10+K$6*J12*(1+Inputs!$C$20) -> 12.270825
A13: EBIT | B13: €m | F13: =F10-F12 -> 13.6 | G13: =G10-G12 -> 16.1 | H13: =H10-H12 -> 18.4 | I13: =I10-I12 -> 19.860375 | J13: =J10-J12 -> 21.38023 | K13: =K10-K12 -> 23.011376
A14: Tax | B14: €m | F14: =F13*Inputs!$C$16 -> 3.264 | G14: =G13*Inputs!$C$16 -> 3.864 | H14: =H13*Inputs!$C$16 -> 4.416 | I14: =I13*Inputs!$C$16 -> 4.76649 | J14: =J13*Inputs!$C$16 -> 5.1312552 | K14: =K13*Inputs!$C$16 -> 5.5227302
A15: NOPAT | B15: €m | F15: =F13-F14 -> 10.336 | G15: =G13-G14 -> 12.236 | H15: =H13-H14 -> 13.984 | I15: =I13-I14 -> 15.093885 | J15: =J13-J14 -> 16.248975 | K15: =K13-K14 -> 17.488646
A16: Capex | B16: €m | F16: =F$5*Inputs!F11+F$6*F8*Inputs!$C$21 -> 12 | G16: =G$5*Inputs!G11+G$6*G8*Inputs!$C$21 -> 13.5 | H16: =H$5*Inputs!H11+H$6*H8*Inputs!$C$21 -> 14.2 | I16: =I$5*Inputs!I11+I$6*I8*Inputs!$C$21 -> 15.398944 | J16: =J$5*Inputs!J11+J$6*J8*Inputs!$C$21 -> 16.430673 | K16: =K$5*Inputs!K11+K$6*K8*Inputs!$C$21 -> 17.531528
A17: Increase in NWC | B17: €m | F17: =F$5*Inputs!F12+F$6*(F8-E8)*Inputs!$C$22 -> 1.2 | G17: =G$5*Inputs!G12+G$6*(G8-F8)*Inputs!$C$22 -> 1.4 | H17: =H$5*Inputs!H12+H$6*(H8-G8)*Inputs!$C$22 -> 1.1 | I17: =I$5*Inputs!I12+I$6*(I8-H8)*Inputs!$C$22 -> 1.20868 | J17: =J$5*Inputs!J12+J$6*(J8-I8)*Inputs!$C$22 -> 1.2896616 | K17: =K$5*Inputs!K12+K$6*(K8-J8)*Inputs!$C$22 -> 1.3760689
A18: Free cash flow | B18: €m | F18: =F15+F12-F16-F17 -> 6.736 | G18: =G15+G12-G16-G17 -> 7.436 | H18: =H15+H12-H16-H17 -> 9.284 | I18: =I15+I12-I16-I17 -> 9.6162608 | J18: =J15+J12-J16-J17 -> 10.21514 | K18: =K15+K12-K16-K17 -> 10.851873
A20: Discount period | B20: years | F20: =F$6*(F4-Inputs!$C$2) -> 0 | G20: =G$6*(G4-Inputs!$C$2) -> 0 | H20: =H$6*(H4-Inputs!$C$2) -> 0 | I20: =I$6*(I4-Inputs!$C$2) -> 1 | J20: =J$6*(J4-Inputs!$C$2) -> 2 | K20: =K$6*(K4-Inputs!$C$2) -> 3
A21: Discount factor | B21: x | F21: =F$6/(1+Inputs!$C$24)^F20 -> 0 | G21: =G$6/(1+Inputs!$C$24)^G20 -> 0 | H21: =H$6/(1+Inputs!$C$24)^H20 -> 0 | I21: =I$6/(1+Inputs!$C$24)^I20 -> 0.92165899 | J21: =J$6/(1+Inputs!$C$24)^J20 -> 0.84945529 | K21: =K$6/(1+Inputs!$C$24)^K20 -> 0.7829081
A22: PV of FCF | B22: €m | F22: =F18*F21 -> 0 | G22: =G18*G21 -> 0 | H22: =H18*H21 -> 0 | I22: =I18*I21 -> 8.8629132 | J22: =J18*J21 -> 8.6773046 | K22: =K18*K21 -> 8.4960196
A24: Terminal value | B24: €m | C24: =K18*(1+Inputs!$C$25)/(Inputs!$C$24-Inputs!$C$25) -> 170.29094
A25: PV of terminal value | B25: €m | C25: =C24*K21 -> 133.32215
A26: Sum of PV of FCF | B26: €m | C26: =SUM(F22:K22) -> 26.036237
A27: Enterprise value | B27: €m | C27: =C25+C26 -> 159.35839
A28: Net debt at the valuation date | B28: €m | C28: =INDEX(Inputs!F13:K13,MATCH(Inputs!$C$2,Inputs!F4:K4,0)) -> 60
A29: Equity value | B29: €m | C29: =C27-C28 -> 99.35839
A30: Shares | B30: m | C30: =INDEX(Inputs!F14:K14,MATCH(Inputs!$C$2,Inputs!F4:K4,0)) -> 40
A31: Value per share | B31: € per share | C31: =C29/C30 -> 2.4839598

Sheet Checks
A1: Checks · every check is a difference that must be 0
A5: Timeline linked | C5: =SUMPRODUCT(ABS(Calc!F4:K4-Inputs!F4:K4)) -> 0
A6: Three actual periods | C6: =ABS(SUM(Inputs!F5:K5)-3) -> 0
A7: Revenue actuals carried over | C7: =SUMPRODUCT(ABS(Calc!F8:H8-Inputs!F8:H8)) -> 0
A8: EBITDA actuals carried over | C8: =SUMPRODUCT(ABS(Calc!F10:H10-Inputs!F9:H9)) -> 0
A9: WACC above terminal growth | C9: =IF(Inputs!C24>Inputs!C25,0,1) -> 0
A10: PV computed two ways | C10: =ABS(Calc!C26-SUMPRODUCT(Calc!F18:K18,Calc!F21:K21)) -> 0
A12: Master check | C12: =IF(MAX(C5:C10)<0.001,0,1) -> 0
